easy_report/__init__.py
easy_report/builder.py
easy_report/utils/__init__.py
easy_report/utils/types.py
easy_report-0.9.dist-info/DESCRIPTION.rst
easy_report-0.9.dist-info/METADATA
easy_report-0.9.dist-info/RECORD
easy_report-0.9.dist-info/WHEEL
easy_report-0.9.dist-info/metadata.json
easy_report-0.9.dist-info/top_level.txt
utils/__init__.py
utils/types.py
