Metadata-Version: 2.0
Name: easy-report
Version: 0.9
Summary: Ease report for devs
Home-page: https://github.com/MrLucasCardoso/easy_report
Author: Lucas Cardoso
Author-email: mr.lucascardoso@gmail.com
License: MIT
Platform: UNKNOWN
Classifier: Environment :: Web Environment
Classifier: Intended Audience :: Developers
Classifier: License :: OSI Approved :: MIT License
Classifier: Operating System :: OS Independent
Classifier: Programming Language :: Python :: 3
Classifier: Programming Language :: Python :: 3.4
Classifier: Programming Language :: Python :: 3.5
Classifier: Topic :: Internet :: WWW/HTTP
Classifier: Topic :: Internet :: WWW/HTTP :: Dynamic Content
Requires-Dist: reportlab (==3.3.0)
